<?xml version="1.0" encoding="UTF-8"?>
<addon:addon id="esphome" xmlns:xsi="http://www.w3.org/2001/XMLSchema-instance"
	xmlns:addon="https://openhab.org/schemas/addon/v1.0.0"
	xsi:schemaLocation="https://openhab.org/schemas/addon/v1.0.0 https://openhab.org/schemas/addon-1.0.0.xsd">

	<type>binding</type>
	<name>ESPHome Binding</name>
	<description>This is the binding for ESPHome native protocol.</description>
	<config-description>
		<parameter name="defaultEncryptionKey" type="text" required="false">
			<context>password</context>
			<label>Default Base64 encoded encryption key for encrypted connection</label>
			<description>Specified in the api: -> encryption: -> key: section of the esphome device config. See
				https://esphome.io/components/api#configuration-variables. Will be used as default if not configured on the device
				thing.</description>
		</parameter>

	</config-description>

</addon:addon>
